web_archive_get/__init__.py
web_archive_get/services/archive.py
web_archive_get/services/arquivo.py
web_archive_get/services/cdx.py
web_archive_get/services/common_crawl_index.py
web_archive_get/services/web_archive.py
web_archive_get-0.1.0.6122.dist-info/METADATA
web_archive_get-0.1.0.6122.dist-info/WHEEL
web_archive_get-0.1.0.6122.dist-info/top_level.txt
web_archive_get-0.1.0.6122.dist-info/RECORD
