Metadata-Version: 2.1
Name: web-archive-get
Version: 0.1.0.6122
Summary: a tool to find archived web pages from different websites using multiple different services
Home-page: https://github.com/WilliamMaber/web_archive_get/
Author: Willdor
Author-email: maberwillliam@gmail.com
License: BSD 2-clause
Platform: UNKNOWN
Classifier: Development Status :: 1 - Planning
Classifier: Intended Audience :: Science/Research
Classifier: License :: OSI Approved :: BSD License
Classifier: Operating System :: POSIX :: Linux
Classifier: Programming Language :: Python :: 2
Classifier: Programming Language :: Python :: 2.7
Classifier: Programming Language :: Python :: 3
Classifier: Programming Language :: Python :: 3.4
Classifier: Programming Language :: Python :: 3.5
Requires-Dist: aiohttp
Requires-Dist: warcio
